dslog/__init__.py
dslog/__init__.pyi
dslog/logger.py
dslog/stdlib.py
dslog/types.py
dslog/formatters/__init__.py
dslog/formatters/__init__.pyi
dslog/formatters/formatters.py
dslog/loggers/__init__.py
dslog/loggers/__init__.pyi
dslog/loggers/_file.py
dslog/loggers/_rich.py
dslog/uvicorn/__init__.py
dslog/uvicorn/__init__.pyi
dslog/uvicorn/config.py
dslog/uvicorn/format.py
dslog/uvicorn/setup.py
dslog/uvicorn/types.py
dslog-0.2.9.dist-info/METADATA
dslog-0.2.9.dist-info/WHEEL
dslog-0.2.9.dist-info/top_level.txt
dslog-0.2.9.dist-info/RECORD
