Metadata-Version: 2.4
Name: dslog
Version: 0.2.9
Summary: Dead-simple logging: what python's logging should've been
Author-email: Marcel Claramunt <marcel@marcelc.uk>
Project-URL: repo, https://github.com/marciclabas/dslog.git
Requires-Python: >=3.10
Requires-Dist: lazy-loader
Provides-Extra: uvicorn
Requires-Dist: uvicorn; extra == "uvicorn"
Provides-Extra: rich
Requires-Dist: rich; extra == "rich"
Provides-Extra: click
Requires-Dist: click; extra == "click"
